{
  "DLSVersion": "2.1.6",
  "Name": "2BIT Counter E",
  "NameLocation": 1,
  "ChipType": 0,
  "Size": {
    "x": 2.45,
    "y": 0.75
  },
  "Colour": {
    "r": 0.172549024,
    "g": 0.258823544,
    "b": 0.2392157,
    "a": 1
  },
  "InputPins":[
    {
      "Name":"Reset",
      "ID":1838310282,
      "Position":{
        "x":-3.375,
        "y":2.8125
      },
      "BitCount":1,
      "Colour":2,
      "ValueDisplayMode":0
    },
    {
      "Name":"CLK",
      "ID":1792590729,
      "Position":{
        "x":-3.375,
        "y":-0.3125
      },
      "BitCount":1,
      "Colour":5,
      "ValueDisplayMode":0
    }
  ],
  "OutputPins":[
    {
      "Name":"E",
      "ID":1588558063,
      "Position":{
        "x":11.375,
        "y":-0.3125
      },
      "BitCount":1,
      "Colour":0,
      "ValueDisplayMode":0
    },
    {
      "Name":"1",
      "ID":908946129,
      "Position":{
        "x":3.875,
        "y":-1.1875
      },
      "BitCount":1,
      "Colour":0,
      "ValueDisplayMode":0
    },
    {
      "Name":"2",
      "ID":1037623790,
      "Position":{
        "x":10.125,
        "y":-1.1875
      },
      "BitCount":1,
      "Colour":0,
      "ValueDisplayMode":0
    }
  ],
  "SubChips":[
    {
      "Name":"D-Flip-Flop-Q2",
      "ID":425942510,
      "Label":"",
      "Position":{
        "x":2.6225,
        "y":-0.1875
      },
      "OutputPinColourInfo":[{"PinColour":0,"PinID":351315061},{"PinColour":4,"PinID":363187466}],
      "InternalData":null
    },
    {
      "Name":"PULSE",
      "ID":1399844762,
      "Label":"",
      "Position":{
        "x":-1.365,
        "y":-0.3125
      },
      "OutputPinColourInfo":[{"PinColour":0,"PinID":1}],
      "InternalData":[1,0,0]
    },
    {
      "Name":"BUS-1",
      "ID":1401363053,
      "Label":"Lock",
      "Position":{
        "x":-3.24,
        "y":2.3125
      },
      "OutputPinColourInfo":null,
      "InternalData":[910188053,0]
    },
    {
      "Name":"BUS-TERMINUS-1",
      "ID":910188053,
      "Label":"Lock",
      "Position":{
        "x":10.135,
        "y":2.3125
      },
      "OutputPinColourInfo":null,
      "InternalData":[1401363053,0]
    },
    {
      "Name":"BUS-1",
      "ID":1535287998,
      "Label":"Reset",
      "Position":{
        "x":-3.24,
        "y":1.6875
      },
      "OutputPinColourInfo":null,
      "InternalData":[1652179385,0]
    },
    {
      "Name":"BUS-TERMINUS-1",
      "ID":1652179385,
      "Label":"Reset",
      "Position":{
        "x":10.135,
        "y":1.6875
      },
      "OutputPinColourInfo":null,
      "InternalData":[1535287998,0]
    },
    {
      "Name":"NOT",
      "ID":51858386,
      "Label":"",
      "Position":{
        "x":-0.4525,
        "y":2.8125
      },
      "OutputPinColourInfo":[{"PinColour":0,"PinID":1930687802}],
      "InternalData":null
    },
    {
      "Name":"PULSE",
      "ID":349542422,
      "Label":"",
      "Position":{
        "x":-1.49,
        "y":2.8125
      },
      "OutputPinColourInfo":[{"PinColour":0,"PinID":1}],
      "InternalData":[5,0,0]
    },
    {
      "Name":"PULSE",
      "ID":2011432072,
      "Label":"",
      "Position":{
        "x":0.635,
        "y":2.8125
      },
      "OutputPinColourInfo":[{"PinColour":1,"PinID":1}],
      "InternalData":[1,0,0]
    },
    {
      "Name":"AND",
      "ID":1547360329,
      "Label":"",
      "Position":{
        "x":-0.265,
        "y":0.0
      },
      "OutputPinColourInfo":[{"PinColour":0,"PinID":1399604186}],
      "InternalData":null
    },
    {
      "Name":"NOT",
      "ID":1442357730,
      "Label":"",
      "Position":{
        "x":-1.2025,
        "y":0.125
      },
      "OutputPinColourInfo":[{"PinColour":0,"PinID":1930687802}],
      "InternalData":null
    },
    {
      "Name":"OR",
      "ID":1906179385,
      "Label":"",
      "Position":{
        "x":0.86,
        "y":-0.0625
      },
      "OutputPinColourInfo":[{"PinColour":0,"PinID":15054840}],
      "InternalData":null
    },
    {
      "Name":"AND",
      "ID":275218599,
      "Label":"",
      "Position":{
        "x":2.36,
        "y":0.6875
      },
      "OutputPinColourInfo":[{"PinColour":0,"PinID":1399604186}],
      "InternalData":null
    },
    {
      "Name":"D-Flip-Flop-Q2",
      "ID":1607340009,
      "Label":"",
      "Position":{
        "x":8.8725,
        "y":-0.1875
      },
      "OutputPinColourInfo":[{"PinColour":0,"PinID":351315061},{"PinColour":4,"PinID":363187466}],
      "InternalData":null
    },
    {
      "Name":"PULSE",
      "ID":700848877,
      "Label":"",
      "Position":{
        "x":4.885,
        "y":-0.3125
      },
      "OutputPinColourInfo":[{"PinColour":0,"PinID":1}],
      "InternalData":[1,0,0]
    },
    {
      "Name":"AND",
      "ID":1089951381,
      "Label":"",
      "Position":{
        "x":5.985,
        "y":0.0
      },
      "OutputPinColourInfo":[{"PinColour":0,"PinID":1399604186}],
      "InternalData":null
    },
    {
      "Name":"NOT",
      "ID":1985403557,
      "Label":"",
      "Position":{
        "x":5.0475,
        "y":0.125
      },
      "OutputPinColourInfo":[{"PinColour":0,"PinID":1930687802}],
      "InternalData":null
    },
    {
      "Name":"OR",
      "ID":1526377331,
      "Label":"",
      "Position":{
        "x":7.11,
        "y":-0.0625
      },
      "OutputPinColourInfo":[{"PinColour":0,"PinID":15054840}],
      "InternalData":null
    },
    {
      "Name":"AND",
      "ID":1689646725,
      "Label":"",
      "Position":{
        "x":8.61,
        "y":0.6875
      },
      "OutputPinColourInfo":[{"PinColour":0,"PinID":1399604186}],
      "InternalData":null
    },
    {
      "Name":"LED",
      "ID":1672624872,
      "Label":"1",
      "Position":{
        "x":3.26,
        "y":-0.75
      },
      "OutputPinColourInfo":[],
      "InternalData":[0]
    },
    {
      "Name":"LED",
      "ID":1415503790,
      "Label":"2",
      "Position":{
        "x":9.51,
        "y":-0.75
      },
      "OutputPinColourInfo":[],
      "InternalData":[0]
    }
  ],
  "Wires":[
    {
      "SourcePinAddress":{
        "PinID":363187466,
        "PinOwnerID":425942510
      },
      "TargetPinAddress":{
        "PinID":1362127412,
        "PinOwnerID":425942510
      },
      "ConnectionType":0,
      "ConnectedWireIndex":-1,
      "ConnectedWireSegmentIndex":-1,
      "Points":[{"x":0.0,"y":0.0},{"x":3.875,"y":-0.3125},{"x":3.875,"y":-0.5},{"x":1.375,"y":-0.5},{"x":1.375,"y":-0.3125},{"x":0.0,"y":0.0}]
    },
    {
      "SourcePinAddress":{
        "PinID":1,
        "PinOwnerID":1401363053
      },
      "TargetPinAddress":{
        "PinID":0,
        "PinOwnerID":910188053
      },
      "ConnectionType":0,
      "ConnectedWireIndex":-1,
      "ConnectedWireSegmentIndex":-1,
      "Points":[{"x":0.0,"y":0.0},{"x":0.0,"y":0.0}]
    },
    {
      "SourcePinAddress":{
        "PinID":1,
        "PinOwnerID":1535287998
      },
      "TargetPinAddress":{
        "PinID":0,
        "PinOwnerID":1652179385
      },
      "ConnectionType":0,
      "ConnectedWireIndex":-1,
      "ConnectedWireSegmentIndex":-1,
      "Points":[{"x":0.0,"y":0.0},{"x":0.0,"y":0.0}]
    },
    {
      "SourcePinAddress":{
        "PinID":0,
        "PinOwnerID":1838310282
      },
      "TargetPinAddress":{
        "PinID":0,
        "PinOwnerID":1401363053
      },
      "ConnectionType":2,
      "ConnectedWireIndex":1,
      "ConnectedWireSegmentIndex":0,
      "Points":[{"x":0.0,"y":0.0},{"x":-2.3125,"y":2.8125},{"x":-2.3125,"y":2.3125}]
    },
    {
      "SourcePinAddress":{
        "PinID":0,
        "PinOwnerID":1838310282
      },
      "TargetPinAddress":{
        "PinID":0,
        "PinOwnerID":349542422
      },
      "ConnectionType":1,
      "ConnectedWireIndex":3,
      "ConnectedWireSegmentIndex":0,
      "Points":[{"x":-2.3125,"y":2.8125},{"x":0.0,"y":0.0}]
    },
    {
      "SourcePinAddress":{
        "PinID":1930687802,
        "PinOwnerID":51858386
      },
      "TargetPinAddress":{
        "PinID":0,
        "PinOwnerID":2011432072
      },
      "ConnectionType":0,
      "ConnectedWireIndex":-1,
      "ConnectedWireSegmentIndex":-1,
      "Points":[{"x":0.0,"y":0.0},{"x":0.0,"y":0.0}]
    },
    {
      "SourcePinAddress":{
        "PinID":1,
        "PinOwnerID":349542422
      },
      "TargetPinAddress":{
        "PinID":992320219,
        "PinOwnerID":51858386
      },
      "ConnectionType":0,
      "ConnectedWireIndex":-1,
      "ConnectedWireSegmentIndex":-1,
      "Points":[{"x":0.0,"y":0.0},{"x":0.0,"y":0.0}]
    },
    {
      "SourcePinAddress":{
        "PinID":1,
        "PinOwnerID":2011432072
      },
      "TargetPinAddress":{
        "PinID":0,
        "PinOwnerID":1535287998
      },
      "ConnectionType":2,
      "ConnectedWireIndex":2,
      "ConnectedWireSegmentIndex":0,
      "Points":[{"x":0.0,"y":0.0},{"x":1.4375,"y":2.8125},{"x":1.4375,"y":1.6875}]
    },
    {
      "SourcePinAddress":{
        "PinID":1930687802,
        "PinOwnerID":1442357730
      },
      "TargetPinAddress":{
        "PinID":1869682709,
        "PinOwnerID":1547360329
      },
      "ConnectionType":0,
      "ConnectedWireIndex":-1,
      "ConnectedWireSegmentIndex":-1,
      "Points":[{"x":0.0,"y":0.0},{"x":0.0,"y":0.0}]
    },
    {
      "SourcePinAddress":{
        "PinID":0,
        "PinOwnerID":1792590729
      },
      "TargetPinAddress":{
        "PinID":0,
        "PinOwnerID":1399844762
      },
      "ConnectionType":0,
      "ConnectedWireIndex":-1,
      "ConnectedWireSegmentIndex":-1,
      "Points":[{"x":0.0,"y":0.0},{"x":0.0,"y":0.0}]
    },
    {
      "SourcePinAddress":{
        "PinID":1,
        "PinOwnerID":1399844762
      },
      "TargetPinAddress":{
        "PinID":1040036612,
        "PinOwnerID":1547360329
      },
      "ConnectionType":0,
      "ConnectedWireIndex":-1,
      "ConnectedWireSegmentIndex":-1,
      "Points":[{"x":0.0,"y":0.0},{"x":-0.75,"y":-0.3125},{"x":-0.75,"y":-0.125},{"x":0.0,"y":0.0}]
    },
    {
      "SourcePinAddress":{
        "PinID":1,
        "PinOwnerID":1401363053
      },
      "TargetPinAddress":{
        "PinID":992320219,
        "PinOwnerID":1442357730
      },
      "ConnectionType":1,
      "ConnectedWireIndex":1,
      "ConnectedWireSegmentIndex":0,
      "Points":[{"x":-1.6875,"y":2.3125},{"x":-1.6875,"y":0.125},{"x":0.0,"y":0.0}]
    },
    {
      "SourcePinAddress":{
        "PinID":1399604186,
        "PinOwnerID":1547360329
      },
      "TargetPinAddress":{
        "PinID":1689109589,
        "PinOwnerID":1906179385
      },
      "ConnectionType":0,
      "ConnectedWireIndex":-1,
      "ConnectedWireSegmentIndex":-1,
      "Points":[{"x":0.0,"y":0.0},{"x":0.3125,"y":0.0},{"x":0.3125,"y":-0.1875},{"x":0.0,"y":0.0}]
    },
    {
      "SourcePinAddress":{
        "PinID":15054840,
        "PinOwnerID":1906179385
      },
      "TargetPinAddress":{
        "PinID":1019384664,
        "PinOwnerID":425942510
      },
      "ConnectionType":0,
      "ConnectedWireIndex":-1,
      "ConnectedWireSegmentIndex":-1,
      "Points":[{"x":0.0,"y":0.0},{"x":0.0,"y":0.0}]
    },
    {
      "SourcePinAddress":{
        "PinID":363187466,
        "PinOwnerID":425942510
      },
      "TargetPinAddress":{
        "PinID":1040036612,
        "PinOwnerID":275218599
      },
      "ConnectionType":1,
      "ConnectedWireIndex":0,
      "ConnectedWireSegmentIndex":0,
      "Points":[{"x":3.875,"y":-0.3125},{"x":3.875,"y":0.1875},{"x":1.8125,"y":0.1875},{"x":1.8125,"y":0.5625},{"x":0.0,"y":0.0}]
    },
    {
      "SourcePinAddress":{
        "PinID":1399604186,
        "PinOwnerID":275218599
      },
      "TargetPinAddress":{
        "PinID":1557984272,
        "PinOwnerID":1906179385
      },
      "ConnectionType":0,
      "ConnectedWireIndex":-1,
      "ConnectedWireSegmentIndex":-1,
      "Points":[{"x":0.0,"y":0.0},{"x":2.9375,"y":0.6875},{"x":2.9375,"y":0.3125},{"x":0.3125,"y":0.3125},{"x":0.3125,"y":0.0625},{"x":0.0,"y":0.0}]
    },
    {
      "SourcePinAddress":{
        "PinID":1,
        "PinOwnerID":1535287998
      },
      "TargetPinAddress":{
        "PinID":1869682709,
        "PinOwnerID":275218599
      },
      "ConnectionType":1,
      "ConnectedWireIndex":2,
      "ConnectedWireSegmentIndex":0,
      "Points":[{"x":1.8125,"y":1.6875},{"x":1.8125,"y":0.8125},{"x":0.0,"y":0.0}]
    },
    {
      "SourcePinAddress":{
        "PinID":363187466,
        "PinOwnerID":1607340009
      },
      "TargetPinAddress":{
        "PinID":1362127412,
        "PinOwnerID":1607340009
      },
      "ConnectionType":0,
      "ConnectedWireIndex":-1,
      "ConnectedWireSegmentIndex":-1,
      "Points":[{"x":0.0,"y":0.0},{"x":10.125,"y":-0.3125},{"x":10.125,"y":-0.5},{"x":7.625,"y":-0.5},{"x":7.625,"y":-0.3125},{"x":0.0,"y":0.0}]
    },
    {
      "SourcePinAddress":{
        "PinID":1930687802,
        "PinOwnerID":1985403557
      },
      "TargetPinAddress":{
        "PinID":1869682709,
        "PinOwnerID":1089951381
      },
      "ConnectionType":0,
      "ConnectedWireIndex":-1,
      "ConnectedWireSegmentIndex":-1,
      "Points":[{"x":0.0,"y":0.0},{"x":0.0,"y":0.0}]
    },
    {
      "SourcePinAddress":{
        "PinID":1,
        "PinOwnerID":700848877
      },
      "TargetPinAddress":{
        "PinID":1040036612,
        "PinOwnerID":1089951381
      },
      "ConnectionType":0,
      "ConnectedWireIndex":-1,
      "ConnectedWireSegmentIndex":-1,
      "Points":[{"x":0.0,"y":0.0},{"x":5.5,"y":-0.3125},{"x":5.5,"y":-0.125},{"x":0.0,"y":0.0}]
    },
    {
      "SourcePinAddress":{
        "PinID":1399604186,
        "PinOwnerID":1089951381
      },
      "TargetPinAddress":{
        "PinID":1689109589,
        "PinOwnerID":1526377331
      },
      "ConnectionType":0,
      "ConnectedWireIndex":-1,
      "ConnectedWireSegmentIndex":-1,
      "Points":[{"x":0.0,"y":0.0},{"x":6.5625,"y":0.0},{"x":6.5625,"y":-0.1875},{"x":0.0,"y":0.0}]
    },
    {
      "SourcePinAddress":{
        "PinID":15054840,
        "PinOwnerID":1526377331
      },
      "TargetPinAddress":{
        "PinID":1019384664,
        "PinOwnerID":1607340009
      },
      "ConnectionType":0,
      "ConnectedWireIndex":-1,
      "ConnectedWireSegmentIndex":-1,
      "Points":[{"x":0.0,"y":0.0},{"x":0.0,"y":0.0}]
    },
    {
      "SourcePinAddress":{
        "PinID":363187466,
        "PinOwnerID":1607340009
      },
      "TargetPinAddress":{
        "PinID":1040036612,
        "PinOwnerID":1689646725
      },
      "ConnectionType":1,
      "ConnectedWireIndex":17,
      "ConnectedWireSegmentIndex":0,
      "Points":[{"x":10.125,"y":-0.3125},{"x":10.125,"y":0.1875},{"x":8.0625,"y":0.1875},{"x":8.0625,"y":0.5625},{"x":0.0,"y":0.0}]
    },
    {
      "SourcePinAddress":{
        "PinID":1399604186,
        "PinOwnerID":1689646725
      },
      "TargetPinAddress":{
        "PinID":1557984272,
        "PinOwnerID":1526377331
      },
      "ConnectionType":0,
      "ConnectedWireIndex":-1,
      "ConnectedWireSegmentIndex":-1,
      "Points":[{"x":0.0,"y":0.0},{"x":9.1875,"y":0.6875},{"x":9.1875,"y":0.3125},{"x":6.5625,"y":0.3125},{"x":6.5625,"y":0.0625},{"x":0.0,"y":0.0}]
    },
    {
      "SourcePinAddress":{
        "PinID":351315061,
        "PinOwnerID":425942510
      },
      "TargetPinAddress":{
        "PinID":0,
        "PinOwnerID":700848877
      },
      "ConnectionType":0,
      "ConnectedWireIndex":-1,
      "ConnectedWireSegmentIndex":-1,
      "Points":[{"x":0.0,"y":0.0},{"x":4.125,"y":-0.0625},{"x":4.125,"y":-0.3125},{"x":0.0,"y":0.0}]
    },
    {
      "SourcePinAddress":{
        "PinID":1,
        "PinOwnerID":1401363053
      },
      "TargetPinAddress":{
        "PinID":992320219,
        "PinOwnerID":1985403557
      },
      "ConnectionType":1,
      "ConnectedWireIndex":1,
      "ConnectedWireSegmentIndex":0,
      "Points":[{"x":4.5625,"y":2.3125},{"x":4.5625,"y":0.125},{"x":0.0,"y":0.0}]
    },
    {
      "SourcePinAddress":{
        "PinID":1,
        "PinOwnerID":1535287998
      },
      "TargetPinAddress":{
        "PinID":1869682709,
        "PinOwnerID":1689646725
      },
      "ConnectionType":1,
      "ConnectedWireIndex":2,
      "ConnectedWireSegmentIndex":0,
      "Points":[{"x":8.0625,"y":1.6875},{"x":8.0625,"y":0.8125},{"x":0.0,"y":0.0}]
    },
    {
      "SourcePinAddress":{
        "PinID":363187466,
        "PinOwnerID":425942510
      },
      "TargetPinAddress":{
        "PinID":0,
        "PinOwnerID":908946129
      },
      "ConnectionType":1,
      "ConnectedWireIndex":0,
      "ConnectedWireSegmentIndex":2,
      "Points":[{"x":2.875,"y":-0.5},{"x":2.875,"y":-1.1875},{"x":0.0,"y":0.0}]
    },
    {
      "SourcePinAddress":{
        "PinID":363187466,
        "PinOwnerID":425942510
      },
      "TargetPinAddress":{
        "PinID":0,
        "PinOwnerID":1672624872
      },
      "ConnectionType":1,
      "ConnectedWireIndex":27,
      "ConnectedWireSegmentIndex":0,
      "Points":[{"x":2.875,"y":-0.75},{"x":0.0,"y":0.0}]
    },
    {
      "SourcePinAddress":{
        "PinID":363187466,
        "PinOwnerID":1607340009
      },
      "TargetPinAddress":{
        "PinID":0,
        "PinOwnerID":1415503790
      },
      "ConnectionType":1,
      "ConnectedWireIndex":17,
      "ConnectedWireSegmentIndex":2,
      "Points":[{"x":9.125,"y":-0.5},{"x":9.125,"y":-0.75},{"x":0.0,"y":0.0}]
    },
    {
      "SourcePinAddress":{
        "PinID":363187466,
        "PinOwnerID":1607340009
      },
      "TargetPinAddress":{
        "PinID":0,
        "PinOwnerID":1037623790
      },
      "ConnectionType":1,
      "ConnectedWireIndex":29,
      "ConnectedWireSegmentIndex":0,
      "Points":[{"x":9.125,"y":-0.75},{"x":9.125,"y":-1.1875},{"x":0.0,"y":0.0}]
    },
    {
      "SourcePinAddress":{
        "PinID":351315061,
        "PinOwnerID":1607340009
      },
      "TargetPinAddress":{
        "PinID":0,
        "PinOwnerID":1588558063
      },
      "ConnectionType":0,
      "ConnectedWireIndex":-1,
      "ConnectedWireSegmentIndex":-1,
      "Points":[{"x":0.0,"y":0.0},{"x":10.375,"y":-0.0625},{"x":10.375,"y":-0.3125},{"x":0.0,"y":0.0}]
    }
  ],
  "Displays":[
    {
      "SubChipID":1672624872,
      "Position":{
        "x":-1.03125,
        "y":-0.15625
      },
      "Scale":1.0
    },
    {
      "SubChipID":1415503790,
      "Position":{
        "x":-0.78125,
        "y":-0.15625
      },
      "Scale":1.0
    }
  ]
}